ChatAIStreamer.py
GttsAIStreamer.py
__init__.py
chatai_streamer-2.0.3.dist-info/LICENSE
chatai_streamer-2.0.3.dist-info/METADATA
chatai_streamer-2.0.3.dist-info/WHEEL
chatai_streamer-2.0.3.dist-info/top_level.txt
chatai_streamer-2.0.3.dist-info/RECORD
